o2despy/__init__.py
o2despy/assets.py
o2despy/event.py
o2despy/hour_counter.py
o2despy/phase_tracker.py
o2despy/pointer.py
o2despy/sandbox.py
o2despy/application/__init__.py
o2despy/application/config.py
o2despy/demos/__init__.py
o2despy/log/__init__.py
o2despy/log/logger.py
qwertywerty123-1234.dist-info/LICENSE
qwertywerty123-1234.dist-info/METADATA
qwertywerty123-1234.dist-info/WHEEL
qwertywerty123-1234.dist-info/top_level.txt
qwertywerty123-1234.dist-info/RECORD
