Metadata-Version: 2.1
Name: qwertywerty123
Version: 1234
Summary: Discrete Event Simulator
Home-page: UNKNOWN
Author: NUS
License: NUS
Platform: UNKNOWN
